vitamin_c_crawler/__init__.py
vitamin_c_crawler/config.py
vitamin_c_crawler/main.py
vitamin_c_crawler/main_script.py
vitamin_c_crawler/pictures_printscreen/data_example.jpg
vitamin_c_crawler/pictures_printscreen/example_csv.jpg
vitamin_c_crawler/pictures_printscreen/pictures_screnshot.jpg
vitamin_c_crawler/vitamin_c_crawler.py
vitamin_c_crawler-2.0.0.dist-info/METADATA
vitamin_c_crawler-2.0.0.dist-info/WHEEL
vitamin_c_crawler-2.0.0.dist-info/RECORD
