Metadata-Version: 2.1
Name: vitamin-c-crawler
Version: 2.0.0
Summary: 
Author: DenisKof82
Author-email: k.denisas@gmail.com
Requires-Python: >=3.10,<4.0
Classifier: Programming Language :: Python :: 3
Classifier: Programming Language :: Python :: 3.10
Classifier: Programming Language :: Python :: 3.11
Classifier: Programming Language :: Python :: 3.12
Requires-Dist: ansible (>=9.1.0,<10.0.0)
